src/__init__.py
src/product_scraper.py
src/vendor_scraper.py
etsy_scraper-0.0.1.dist-info/LICENSE
etsy_scraper-0.0.1.dist-info/METADATA
etsy_scraper-0.0.1.dist-info/WHEEL
etsy_scraper-0.0.1.dist-info/top_level.txt
etsy_scraper-0.0.1.dist-info/RECORD
