Metadata-Version: 2.1
Name: etsy-scraper
Version: 0.0.1
Summary: Retrieves info from Etsy using UrlLib and Beautiful Soup and returns the data in JSON.
Home-page: https://github.com/Dahmer-Open/etsy-scraper
Author: Dominic Fournier
Author-email: me@dominicfournier.com
License: UNKNOWN
Platform: UNKNOWN
Classifier: Programming Language :: Python :: 3
Classifier: Programming Language :: Python :: 3.6
Classifier: Programming Language :: Python :: 3.7
Classifier: License :: OSI Approved :: MIT License
Classifier: Operating System :: OS Independent
Requires-Python: >=3.6
Requires-Dist: beautifulsoup4
